jprinter/__init__.py
jprinter/jjprinter.py
jjprinter-0.1.0.dist-info/METADATA
jjprinter-0.1.0.dist-info/WHEEL
jjprinter-0.1.0.dist-info/top_level.txt
jjprinter-0.1.0.dist-info/RECORD
