Metadata-Version: 2.4
Name: JJprinter
Version: 0.1.0
Summary: Janek's easy printing module
Author: janektech.pl
License: MIT
Requires-Python: >=3.8
